nmf_standalone/__init__.py
nmf_standalone/cli.py
nmf_standalone/standalone_nmf.py
nmf_standalone/_functions/__init__.py
nmf_standalone/_functions/common_language/__init__.py
nmf_standalone/_functions/common_language/emoji_processor.py
nmf_standalone/_functions/common_language/topic_analyzer.py
nmf_standalone/_functions/english/__init__.py
nmf_standalone/_functions/english/english_nmf_core.py
nmf_standalone/_functions/english/english_preprocessor.py
nmf_standalone/_functions/english/english_text_encoder.py
nmf_standalone/_functions/english/english_topic_analyzer.py
nmf_standalone/_functions/english/english_topic_output.py
nmf_standalone/_functions/english/english_vocabulary.py
nmf_standalone/_functions/nmf/__init__.py
nmf_standalone/_functions/nmf/nmf_basic.py
nmf_standalone/_functions/nmf/nmf_initialization.py
nmf_standalone/_functions/nmf/nmf_orchestrator.py
nmf_standalone/_functions/nmf/nmf_projective_basic.py
nmf_standalone/_functions/nmf/nmf_projective_enhanced.py
nmf_standalone/_functions/tfidf/__init__.py
nmf_standalone/_functions/tfidf/tfidf_bm25_turkish.py
nmf_standalone/_functions/tfidf/tfidf_english_calculator.py
nmf_standalone/_functions/tfidf/tfidf_idf_functions.py
nmf_standalone/_functions/tfidf/tfidf_tf_functions.py
nmf_standalone/_functions/tfidf/tfidf_turkish_calculator.py
nmf_standalone/_functions/turkish/__init__.py
nmf_standalone/_functions/turkish/turkish_preprocessor.py
nmf_standalone/_functions/turkish/turkish_text_encoder.py
nmf_standalone/_functions/turkish/turkish_tfidf_generator.py
nmf_standalone/_functions/turkish/turkish_tokenizer_factory.py
nmf_standalone/utils/__init__.py
nmf_standalone/utils/backup.py
nmf_standalone/utils/coherence_score.py
nmf_standalone/utils/distance_two_words.py
nmf_standalone/utils/export_excel.py
nmf_standalone/utils/gen_cloud.py
nmf_standalone/utils/hierarchy_nmf.py
nmf_standalone/utils/image_to_base.py
nmf_standalone/utils/redis_bridge.py
nmf_standalone/utils/save_doc_score_pair.py
nmf_standalone-0.3.4.post2.dist-info/licenses/LICENSE
nmf_standalone-0.3.4.post2.dist-info/METADATA
nmf_standalone-0.3.4.post2.dist-info/WHEEL
nmf_standalone-0.3.4.post2.dist-info/entry_points.txt
nmf_standalone-0.3.4.post2.dist-info/top_level.txt
nmf_standalone-0.3.4.post2.dist-info/RECORD
