Metadata-Version: 2.4
Name: nmf-standalone
Version: 0.3.4.post2
Summary: A standalone NMF topic modeling tool for Turkish and English texts
Author-email: Emir Karayagiz <emirkyzmain@gmail.com>
License-Expression: MIT
Project-URL: Homepage, https://github.com/emirkyz/nmf-standalone/tree/main/nmf-standalone-pypi
Project-URL: Repository, https://github.com/emirkyz/nmf-standalone/tree/main/nmf-standalone-pypi
Project-URL: Documentation, https://github.com/emirkarayagiz/nmf-standalone#readme
Project-URL: Issues, https://github.com/emirkyz/nmf-standalone/issues?q=is%3Aissue
Keywords: nlp,topic-modeling,nmf,text-analysis,turkish,english
Classifier: Development Status :: 4 - Beta
Classifier: Intended Audience :: Science/Research
Classifier: Intended Audience :: Developers
Classifier: Operating System :: OS Independent
Classifier: Programming Language :: Python :: 3
Classifier: Programming Language :: Python :: 3.9
Classifier: Programming Language :: Python :: 3.10
Classifier: Programming Language :: Python :: 3.11
Classifier: Programming Language :: Python :: 3.12
Classifier: Topic :: Scientific/Engineering :: Artificial Intelligence
Classifier: Topic :: Text Processing :: Linguistic
Requires-Python: >=3.11
License-File: LICENSE
Requires-Dist: emoji~=2.14.1
Requires-Dist: gensim==4.3.2
Requires-Dist: levenshtein==0.20.9
Requires-Dist: matplotlib==3.10.1
Requires-Dist: nltk==3.8.1
Requires-Dist: numpy==1.26.4
Requires-Dist: pandas==2.2.1
Requires-Dist: pillow==11.1.0
Requires-Dist: redis==5.0.1
Requires-Dist: scikit-learn==1.3.2
Requires-Dist: scipy==1.10.1
Requires-Dist: seaborn~=0.13.2
Requires-Dist: sqlalchemy==2.0.27
Requires-Dist: tokenizers==0.21.1
Requires-Dist: wordcloud==1.9.4
Provides-Extra: dev
Requires-Dist: pytest>=7.0.0; extra == "dev"
Requires-Dist: black>=23.0.0; extra == "dev"
Requires-Dist: flake8>=6.0.0; extra == "dev"
Requires-Dist: mypy>=1.0.0; extra == "dev"
Dynamic: license-file
